beaker/__init__.py
beaker/cleanup.yml
beaker/main.yml
beaker/plugin.spec
beaker/provision.yml
beaker/library/beaker_provisioner.py
beaker/vars/image/rhel-7.2.yml
beaker/vars/image/rhel-7.3.yml
beaker/vars/image/rhel-7.4.yml
beaker/vars/image/sample.yml.example
infrared_beaker-3.0.0.dist-info/DESCRIPTION.rst
infrared_beaker-3.0.0.dist-info/METADATA
infrared_beaker-3.0.0.dist-info/RECORD
infrared_beaker-3.0.0.dist-info/WHEEL
infrared_beaker-3.0.0.dist-info/entry_points.txt
infrared_beaker-3.0.0.dist-info/metadata.json
infrared_beaker-3.0.0.dist-info/pbr.json
infrared_beaker-3.0.0.dist-info/top_level.txt
